{"title":"JAX-RSをやってみる (6) - 例外処理 -","keywords":["JAX","package","import","public","throw","protected","return","Response","assertThat"],"similarity":[{"title":"JAX-RSをやってみる (10) - AsyncResponse -","permalink":"/2014/06/jaxrs-10-asyncresponse.html"},{"title":"JAX-RSをやってみる (4) - MessageBodyReader -","permalink":"/2014/06/jaxrs-4-messagebodyreader.html"},{"title":"JAX-RSをやってみる (11) - Server Sent Events -","permalink":"/2014/06/jaxrs-11-server-sent-events.html"},{"title":"Mockitoでfinalクラスをモック化 (2)","permalink":"/2013/10/mockito-mocked-final-class-2.html"},{"title":"Androidアプリ上でのサーチハードウェアキーによる振る舞い機能を実装","permalink":"/2013/01/android-search-hardware-key-suggestion.html"}]}