{"title":"Androidでengine.io","keywords":["Socket","Emitter","java","byte"],"similarity":[{"title":"HttpClientクラスで「java.io.IOException: Attempted read from closed stream」が出るケース","permalink":"/2013/04/android-httpclient-ioexception-attempted-read-from-closed.html"},{"title":"gradle-android-test-plugin","permalink":"/2014/01/gradle-android-test-plugin.html"},{"title":"ActionBar-PullToRefresh","permalink":"/2014/02/actionbar-pulltorefresh.html"},{"title":"LoadMoreListView","permalink":"/2014/02/loadmorelistview.html"},{"title":"Espressoを使ったUIテスト","permalink":"/2014/04/android-espresso-ui-testing.html"}]}