{"title":"thymeleaf","keywords":["thymeleaf","日本語","ゲッターメソッド","http","Stat","html"],"similarity":[{"title":"Mockitoでfinalクラスをモック化","permalink":"/2013/06/mockito-mocked-final-class.html"},{"title":"arquillian-remote","permalink":"/2014/09/arquillian-remote-testing.html"},{"title":"mock-javamail","permalink":"/2014/01/mock-javamail.html"},{"title":"Annotation Processorの基本的な所","permalink":"/2013/11/java-annotation-processor.html"},{"title":"thymeleaf+spring mvc","permalink":"/2014/01/thymeleaf-spring-framework-webmvc.html"}]}